robotframework_archive/__init__.py
robotframework_archive/app.py
robotframework_archive/args.py
robotframework_archive/rfarchivesetup.py
robotframework_archive/setupargs.py
robotframework_archive/historic/parserargs.py
robotframework_archive/historic/reparserargs.py
robotframework_archive/historic/rfhistoricparser.py
robotframework_archive/historic/rfhistoricreparser.py
robotframework_archive/sf_historic/parserargs.py
robotframework_archive/sf_historic/sfhistoricparser.py
robotframework_archive/sp_historic/parserargs.py
robotframework_archive/sp_historic/sphistoricparser.py
robotframework_archive/templates/home.html
robotframework_archive/templates/hs__.html
robotframework_archive/templates/hscomment.html
robotframework_archive/templates/hscompare.html
robotframework_archive/templates/hsdashboardAll.html
robotframework_archive/templates/hsdashboardByEid.html
robotframework_archive/templates/hsdashboardRecent.html
robotframework_archive/templates/hsdashboardRecentFive.html
robotframework_archive/templates/hsdashboardRecentTen.html
robotframework_archive/templates/hsdashboardRecentThirty.html
robotframework_archive/templates/hsdeldbconf.html
robotframework_archive/templates/hsdeleconf.html
robotframework_archive/templates/hsehistoric.html
robotframework_archive/templates/hseidtmetrics.html
robotframework_archive/templates/hsfailures.html
robotframework_archive/templates/hsflaky.html
robotframework_archive/templates/hshome.html
robotframework_archive/templates/hsnew.html
robotframework_archive/templates/hssearch.html
robotframework_archive/templates/hstmetrics.html
robotframework_archive/templates/hsttags.html
robotframework_archive/templates/redirect.html
robotframework_archive/templates/sf__.html
robotframework_archive/templates/sfcmetrics.html
robotframework_archive/templates/sfdashboardRecent.html
robotframework_archive/templates/sfdashboardRecentTwo.html
robotframework_archive/templates/sfdeldbconf.html
robotframework_archive/templates/sfdeleconf.html
robotframework_archive-0.0.5.dist-info/LICENSE
robotframework_archive-0.0.5.dist-info/METADATA
robotframework_archive-0.0.5.dist-info/WHEEL
robotframework_archive-0.0.5.dist-info/entry_points.txt
robotframework_archive-0.0.5.dist-info/top_level.txt
robotframework_archive-0.0.5.dist-info/RECORD
